pyvenv/__init__.py
pyvenv/functions.py
pyvenv/main.py
pyvenv/utils.py
pyvenv-0.2.1.dist-info/entry_points.txt
pyvenv-0.2.1.dist-info/WHEEL
pyvenv-0.2.1.dist-info/METADATA
pyvenv-0.2.1.dist-info/RECORD
