Metadata-Version: 2.1
Name: pyvenv
Version: 0.2.1
Summary: A minimalist python environment manager.
Home-page: https://github.com/Ashrit-Yarava/pyvenv
License: MIT
Keywords: pyvenv,environment,venv,pyenv,env
Author: Ashrit Yarava
Author-email: ashdragon95@gmail.com
Requires-Python: >=3.6,<4.0
Classifier: License :: OSI Approved :: MIT License
Classifier: Programming Language :: Python :: 3
Classifier: Programming Language :: Python :: 3.6
Classifier: Programming Language :: Python :: 3.7
Classifier: Programming Language :: Python :: 3.8
Requires-Dist: clipboard (>=0.0.4,<0.0.5)
Requires-Dist: termcolor (>=1.1.0,<2.0.0)
